scriptpilot/__init__.py
scriptpilot/__main__.py
scriptpilot/main.py
scriptpilot-1.2.2.dist-info/METADATA
scriptpilot-1.2.2.dist-info/WHEEL
scriptpilot-1.2.2.dist-info/entry_points.txt
scriptpilot-1.2.2.dist-info/top_level.txt
scriptpilot-1.2.2.dist-info/RECORD
