Metadata-Version: 2.1
Name: scriptpilot
Version: 1.2.2
Summary: A tool to manage the execution of multiple Python scripts.
Home-page: https://github.com/yourusername/scriptpilot
Author: Javer Valino
Classifier: Programming Language :: Python :: 3
Classifier: License :: OSI Approved :: MIT License
Classifier: Operating System :: OS Independent
Requires-Python: >=3.6
Requires-Dist: fastapi
Requires-Dist: fastapi-cors
Requires-Dist: uvicorn
Requires-Dist: pydantic
Requires-Dist: psutil
